{
  "coord": {
    "lon": -49.4858,
    "lat": -28.9347
  },
  "weather": [
    {
      "id": 801,
      "main": "Clouds",
      "description": "few clouds",
      "icon": "02d"
    }
  ],
  "base": "stations",
  "main": {
    "temp": 24.13,
    "feels_like": 24.5,
    "temp_min": 24.13,
    "temp_max": 24.13,
    "pressure": 1011,
    "humidity": 73,
    "sea_level": 1011,
    "grnd_level": 1011
  },
  "visibility": 10000,
  "wind": {
    "speed": 3.15,
    "deg": 237,
    "gust": 5.98
  },
  "clouds": {
    "all": 18
  },
  "dt": 1769769840,
  "sys": {
    "country": "BR",
    "sunrise": 1769762796,
    "sunset": 1769811342
  },
  "timezone": -10800,
  "id": 3471772,
  "name": "Araranguá",
  "cod": 200,
  "_last_updated_utc": "2026-01-30T10:44:00.884Z"
}