{
  "coord": {
    "lon": -49.4858,
    "lat": -28.9347
  },
  "weather": [
    {
      "id": 800,
      "main": "Clear",
      "description": "clear sky",
      "icon": "01n"
    }
  ],
  "base": "stations",
  "main": {
    "temp": 25.72,
    "feels_like": 26.54,
    "temp_min": 25.72,
    "temp_max": 25.72,
    "pressure": 1012,
    "humidity": 84,
    "sea_level": 1012,
    "grnd_level": 1012
  },
  "visibility": 10000,
  "wind": {
    "speed": 1.27,
    "deg": 3,
    "gust": 1.44
  },
  "clouds": {
    "all": 0
  },
  "dt": 1770886643,
  "sys": {
    "country": "BR",
    "sunrise": 1770886645,
    "sunset": 1770934027
  },
  "timezone": -10800,
  "id": 3471772,
  "name": "Araranguá",
  "cod": 200,
  "_last_updated_utc": "2026-02-12T08:57:23.612Z"
}