{
  "coord": {
    "lon": -49.4858,
    "lat": -28.9347
  },
  "weather": [
    {
      "id": 803,
      "main": "Clouds",
      "description": "broken clouds",
      "icon": "04d"
    }
  ],
  "base": "stations",
  "main": {
    "temp": 28.81,
    "feels_like": 31.32,
    "temp_min": 28.81,
    "temp_max": 28.81,
    "pressure": 1014,
    "humidity": 64,
    "sea_level": 1014,
    "grnd_level": 1014
  },
  "visibility": 10000,
  "wind": {
    "speed": 3.06,
    "deg": 107,
    "gust": 4.86
  },
  "clouds": {
    "all": 76
  },
  "dt": 1770583021,
  "sys": {
    "country": "BR",
    "sunrise": 1770540851,
    "sunset": 1770588609
  },
  "timezone": -10800,
  "id": 3471772,
  "name": "Araranguá",
  "cod": 200,
  "_last_updated_utc": "2026-02-08T20:37:01.853Z"
}