{
  "coord": {
    "lon": -49.4858,
    "lat": -28.9347
  },
  "weather": [
    {
      "id": 800,
      "main": "Clear",
      "description": "clear sky",
      "icon": "01d"
    }
  ],
  "base": "stations",
  "main": {
    "temp": 28.68,
    "feels_like": 29.97,
    "temp_min": 28.68,
    "temp_max": 28.68,
    "pressure": 1019,
    "humidity": 56,
    "sea_level": 1019,
    "grnd_level": 1017
  },
  "visibility": 10000,
  "wind": {
    "speed": 2.6,
    "deg": 104,
    "gust": 2.51
  },
  "clouds": {
    "all": 0
  },
  "dt": 1769264832,
  "sys": {
    "country": "BR",
    "sunrise": 1769244084,
    "sunset": 1769293100
  },
  "timezone": -10800,
  "id": 3471772,
  "name": "Araranguá",
  "cod": 200,
  "_last_updated_utc": "2026-01-24T14:27:12.920Z"
}